busy/__init__.py
busy/__main__.py
busy/command/__init__.py
busy/command/activate_command.py
busy/command/add_command.py
busy/command/defer_command.py
busy/command/delete_command.py
busy/command/describe_command.py
busy/command/done_command.py
busy/command/drop_and_pop_command.py
busy/command/dump_command.py
busy/command/edit_command.py
busy/command/list_command.py
busy/command/mcp_command.py
busy/command/print_command.py
busy/command/queues_command.py
busy/command/report_command.py
busy/command/simple_command.py
busy/command/tags_command.py
busy/command/view_command.py
busy/error.py
busy/model/__init__.py
busy/model/collection/__init__.py
busy/model/collection/done_collection.py
busy/model/collection/plan_collection.py
busy/model/collection/todo_collection.py
busy/model/configured.py
busy/model/item.py
busy/storage/__init__.py
busy/storage/file_storage.py
busy/test_case.py
busy/util/__init__.py
busy/util/checklist.py
busy/util/date_util.py
busy/util/edit.py
busy/util/identifier.py
busy/util/python_version.py
busy/util/selector.py
busy-7.14.6.dist-info/METADATA
busy-7.14.6.dist-info/WHEEL
busy-7.14.6.dist-info/entry_points.txt
busy-7.14.6.dist-info/licenses/LICENSE
busy-7.14.6.dist-info/RECORD
