Metadata-Version: 2.4
Name: busy
Version: 7.14.6
Summary: Escape from overwhelm and stay focused all day
License: MIT
License-File: LICENSE
Author: Steampunk Wizard
Author-email: busy@steamwiz.io
Requires-Python: >=3.11,<4.0
Classifier: License :: OSI Approved :: MIT License
Classifier: Programming Language :: Python :: 3
Classifier: Programming Language :: Python :: 3.11
Classifier: Programming Language :: Python :: 3.12
Classifier: Programming Language :: Python :: 3.13
Classifier: Programming Language :: Python :: 3.14
Requires-Dist: jinja2 (>=3.1.6,<4.0.0)
Requires-Dist: mcp[cli] (>=1.2.0,<2.0.0)
Requires-Dist: platformdirs (>=3.10.0,<4.0.0)
Requires-Dist: pyyaml (>=6.0,<7.0)
Requires-Dist: reportlab (>=4.0.4,<5.0.0)
Requires-Dist: wizlib (>=3.3.8,<3.4.0)
Project-URL: Homepage, https://steamwiz.io
Project-URL: Repository, https://gitlab.com/steamwiz/busy
